{
  "protocol": {
    "dataset": "EuroSAT_MS",
    "split": "80/10/10 matched protocol",
    "query_split": "val",
    "gallery_split": "test",
    "seed": 42,
    "max_queries": null,
    "max_gallery": null
  },
  "pipeline": {
    "sigma": 0.5,
    "num_steps": 5,
    "lr": 0.01,
    "lambda_m": 0.1,
    "k": 5,
    "grad_clip": 1.0,
    "early_stop_tol": 1e-06,
    "query_conditioning": "class_text_embedding"
  },
  "artifacts": {
    "table_csv": "results/ablation/component_ablation_table.csv",
    "waterfall_png": "results/ablation/component_ablation_waterfall.png",
    "analysis_txt": "results/ablation/component_contribution_analysis.txt",
    "query_band_cache": "results/matched_protocol/eurosat_matched_protocol_query_band_embeddings.pt",
    "gallery_band_cache": "results/matched_protocol/eurosat_matched_protocol_gallery_band_embeddings.pt",
    "rgb_query_cache": "results/ablation/component_ablation_rgb_query_features.pt",
    "rgb_gallery_cache": "results/ablation/component_ablation_rgb_gallery_features.pt"
  },
  "rows": [
    {
      "stage_order": 1,
      "component": "No per-band (RGB baseline)",
      "configuration": "RGB-CLIP image-to-image",
      "query_split": "val",
      "gallery_split": "test",
      "num_queries": 2700,
      "num_gallery": 2700,
      "fusion_mean_ms_query": 0.0,
      "fusion_mean_ms_gallery": 0.0,
      "mean_weight_entropy": "",
      "R@1": 79.11111116409302,
      "R@5": 94.5555567741394,
      "R@10": 97.18518257141113,
      "mAP": 41.0467058232537,
      "delta_R@1_vs_rgb": 0.0,
      "delta_R@10_vs_rgb": 0.0,
      "incremental_delta_R@1": 0.0,
      "incremental_delta_R@10": 0.0,
      "redundant_by_R@1": false
    },
    {
      "stage_order": 2,
      "component": "+ Per-band encode",
      "configuration": "Uniform mean of 13 per-band CLIP embeddings",
      "query_split": "val",
      "gallery_split": "test",
      "num_queries": 2700,
      "num_gallery": 2700,
      "fusion_mean_ms_query": 0.010150118269612667,
      "fusion_mean_ms_gallery": 0.009008590401477974,
      "mean_weight_entropy": 2.5649490356445312,
      "R@1": 84.11111235618591,
      "R@5": 96.85184955596924,
      "R@10": 98.629629611969,
      "mAP": 46.85140422924801,
      "delta_R@1_vs_rgb": 5.0000011920928955,
      "delta_R@10_vs_rgb": 1.4444470405578613,
      "incremental_delta_R@1": 5.0000011920928955,
      "incremental_delta_R@10": 1.4444470405578613,
      "redundant_by_R@1": false
    },
    {
      "stage_order": 3,
      "component": "+ Affinity graph",
      "configuration": "Query-alignment softmax band weights",
      "query_split": "val",
      "gallery_split": "test",
      "num_queries": 2700,
      "num_gallery": 2700,
      "fusion_mean_ms_query": 0.04080535354592872,
      "fusion_mean_ms_gallery": 0.032419182038952214,
      "mean_weight_entropy": 2.5638322830200195,
      "R@1": 83.88888835906982,
      "R@5": 96.81481719017029,
      "R@10": 98.55555295944214,
      "mAP": 47.10546205786091,
      "delta_R@1_vs_rgb": 4.777777194976807,
      "delta_R@10_vs_rgb": 1.3703703880310059,
      "incremental_delta_R@1": -0.22222399711608887,
      "incremental_delta_R@10": -0.07407665252685547,
      "redundant_by_R@1": true
    },
    {
      "stage_order": 4,
      "component": "+ Fiedler",
      "configuration": "Fiedler magnitude weights, no manifold optimization",
      "query_split": "val",
      "gallery_split": "test",
      "num_queries": 2700,
      "num_gallery": 2700,
      "fusion_mean_ms_query": 0.08812063330508492,
      "fusion_mean_ms_gallery": 0.08771814022178727,
      "mean_weight_entropy": 2.324293375015259,
      "R@1": 83.22222232818604,
      "R@5": 96.22222185134888,
      "R@10": 98.59259128570557,
      "mAP": 44.752590512373935,
      "delta_R@1_vs_rgb": 4.111111164093018,
      "delta_R@10_vs_rgb": 1.4074087142944336,
      "incremental_delta_R@1": -0.6666660308837891,
      "incremental_delta_R@10": 0.037038326263427734,
      "redundant_by_R@1": true
    },
    {
      "stage_order": 5,
      "component": "+ Manifold optimization",
      "configuration": "Full Fiedler + manifold optimization pipeline",
      "query_split": "val",
      "gallery_split": "test",
      "num_queries": 2700,
      "num_gallery": 2700,
      "fusion_mean_ms_query": 1.2321182719487869,
      "fusion_mean_ms_gallery": 1.2822881235991157,
      "mean_weight_entropy": 2.3444265127182007,
      "R@1": 83.14814567565918,
      "R@5": 96.29629850387573,
      "R@10": 98.44444394111633,
      "mAP": 45.25504702867733,
      "delta_R@1_vs_rgb": 4.037034511566162,
      "delta_R@10_vs_rgb": 1.2592613697052002,
      "incremental_delta_R@1": -0.07407665252685547,
      "incremental_delta_R@10": -0.1481473445892334,
      "redundant_by_R@1": true
    }
  ]
}